{
  "stage_id": "Lv3-P6-S27",
  "title": "강조 부사",
  "description": "really, actually, absolutely, exactly 같은 강조 부사/말버릇을 익혀 말의 강도를 조절합니다. 회화에서 자주 쓰이는 이러한 단어들을 적절히 끼워 넣어 말해보며, 감정과 확신을 효과적으로 전달하는 방법을 배웁니다.",
  "grammar_pattern": "really + 형용사/부사 / actually + 문장 / absolutely + 형용사 / exactly + 문장",
  "examples": ["I really like this song.", "It's absolutely amazing.", "That's exactly what I mean.", "Actually, I disagree."],
  "learning_points": "강조 부사별 미묘한 뉘앙스 차이와 적절한 사용 상황",
  "phase": 6,
  "stage_number": 27,
  "count": 0,
  "sentences": []
}