{
  "stage_id": "Lv6-D4-S23",
  "title": "파생상품 및 위험관리",
  "count": 50,
  "sentences": [
    {
      "id": "Lv6-D4-S23-001",
      "kr": "파생상품 포트폴리오가 구성되었습니다. (완성 1)",
      "en": "A derivatives portfolio has been constructed. (completion variant 1)",
      "form": "aff",
      "grammar_tags": [
        "DERIVATIVES-TERMINOLOGY",
        "RISK-LANGUAGE",
        "QUANTITATIVE-TERMS",
        "HEDGING-CONCEPTS"
      ]
    },
    {
      "id": "Lv6-D4-S23-002",
      "kr": "파생상품 포트폴리오가 구성되었습니다. (완성 2)",
      "en": "A derivatives portfolio has been constructed. (completion variant 2)",
      "form": "aff",
      "grammar_tags": [
        "DERIVATIVES-TERMINOLOGY",
        "RISK-LANGUAGE",
        "QUANTITATIVE-TERMS",
        "HEDGING-CONCEPTS"
      ]
    },
    {
      "id": "Lv6-D4-S23-003",
      "kr": "파생상품 포트폴리오가 구성되었습니다. (완성 3)",
      "en": "A derivatives portfolio has been constructed. (completion variant 3)",
      "form": "aff",
      "grammar_tags": [
        "DERIVATIVES-TERMINOLOGY",
        "RISK-LANGUAGE",
        "QUANTITATIVE-TERMS",
        "HEDGING-CONCEPTS"
      ]
    },
    {
      "id": "Lv6-D4-S23-004",
      "kr": "파생상품 포트폴리오가 구성되었습니다. (완성 4)",
      "en": "A derivatives portfolio has been constructed. (completion variant 4)",
      "form": "aff",
      "grammar_tags": [
        "DERIVATIVES-TERMINOLOGY",
        "RISK-LANGUAGE",
        "QUANTITATIVE-TERMS",
        "HEDGING-CONCEPTS"
      ]
    },
    {
      "id": "Lv6-D4-S23-005",
      "kr": "파생상품 포트폴리오가 구성되었습니다. (완성 5)",
      "en": "A derivatives portfolio has been constructed. (completion variant 5)",
      "form": "aff",
      "grammar_tags": [
        "DERIVATIVES-TERMINOLOGY",
        "RISK-LANGUAGE",
        "QUANTITATIVE-TERMS",
        "HEDGING-CONCEPTS"
      ]
    },
    {
      "id": "Lv6-D4-S23-006",
      "kr": "위험을 헤지하기 위한 전략을 수립했습니다. (완성 1)",
      "en": "We have established a strategy to hedge risks. (completion variant 1)",
      "form": "aff",
      "grammar_tags": [
        "DERIVATIVES-TERMINOLOGY",
        "RISK-LANGUAGE",
        "QUANTITATIVE-TERMS",
        "HEDGING-CONCEPTS"
      ]
    },
    {
      "id": "Lv6-D4-S23-007",
      "kr": "위험을 헤지하기 위한 전략을 수립했습니다. (완성 2)",
      "en": "We have established a strategy to hedge risks. (completion variant 2)",
      "form": "aff",
      "grammar_tags": [
        "DERIVATIVES-TERMINOLOGY",
        "RISK-LANGUAGE",
        "QUANTITATIVE-TERMS",
        "HEDGING-CONCEPTS"
      ]
    },
    {
      "id": "Lv6-D4-S23-008",
      "kr": "위험을 헤지하기 위한 전략을 수립했습니다. (완성 3)",
      "en": "We have established a strategy to hedge risks. (completion variant 3)",
      "form": "aff",
      "grammar_tags": [
        "DERIVATIVES-TERMINOLOGY",
        "RISK-LANGUAGE",
        "QUANTITATIVE-TERMS",
        "HEDGING-CONCEPTS"
      ]
    },
    {
      "id": "Lv6-D4-S23-009",
      "kr": "위험을 헤지하기 위한 전략을 수립했습니다. (완성 4)",
      "en": "We have established a strategy to hedge risks. (completion variant 4)",
      "form": "aff",
      "grammar_tags": [
        "DERIVATIVES-TERMINOLOGY",
        "RISK-LANGUAGE",
        "QUANTITATIVE-TERMS",
        "HEDGING-CONCEPTS"
      ]
    },
    {
      "id": "Lv6-D4-S23-010",
      "kr": "위험을 헤지하기 위한 전략을 수립했습니다. (완성 5)",
      "en": "We have established a strategy to hedge risks. (completion variant 5)",
      "form": "aff",
      "grammar_tags": [
        "DERIVATIVES-TERMINOLOGY",
        "RISK-LANGUAGE",
        "QUANTITATIVE-TERMS",
        "HEDGING-CONCEPTS"
      ]
    },
    {
      "id": "Lv6-D4-S23-011",
      "kr": "스왑 계약이 체결되었습니다. (완성 1)",
      "en": "A swap contract has been concluded. (completion variant 1)",
      "form": "aff",
      "grammar_tags": [
        "DERIVATIVES-TERMINOLOGY",
        "RISK-LANGUAGE",
        "QUANTITATIVE-TERMS",
        "HEDGING-CONCEPTS"
      ]
    },
    {
      "id": "Lv6-D4-S23-012",
      "kr": "스왑 계약이 체결되었습니다. (완성 2)",
      "en": "A swap contract has been concluded. (completion variant 2)",
      "form": "aff",
      "grammar_tags": [
        "DERIVATIVES-TERMINOLOGY",
        "RISK-LANGUAGE",
        "QUANTITATIVE-TERMS",
        "HEDGING-CONCEPTS"
      ]
    },
    {
      "id": "Lv6-D4-S23-013",
      "kr": "스왑 계약이 체결되었습니다. (완성 3)",
      "en": "A swap contract has been concluded. (completion variant 3)",
      "form": "aff",
      "grammar_tags": [
        "DERIVATIVES-TERMINOLOGY",
        "RISK-LANGUAGE",
        "QUANTITATIVE-TERMS",
        "HEDGING-CONCEPTS"
      ]
    },
    {
      "id": "Lv6-D4-S23-014",
      "kr": "스왑 계약이 체결되었습니다. (완성 4)",
      "en": "A swap contract has been concluded. (completion variant 4)",
      "form": "aff",
      "grammar_tags": [
        "DERIVATIVES-TERMINOLOGY",
        "RISK-LANGUAGE",
        "QUANTITATIVE-TERMS",
        "HEDGING-CONCEPTS"
      ]
    },
    {
      "id": "Lv6-D4-S23-015",
      "kr": "스왑 계약이 체결되었습니다. (완성 5)",
      "en": "A swap contract has been concluded. (completion variant 5)",
      "form": "aff",
      "grammar_tags": [
        "DERIVATIVES-TERMINOLOGY",
        "RISK-LANGUAGE",
        "QUANTITATIVE-TERMS",
        "HEDGING-CONCEPTS"
      ]
    },
    {
      "id": "Lv6-D4-S23-016",
      "kr": "옵션 거래가 실행되었습니다. (완성 1)",
      "en": "Options trading has been executed. (completion variant 1)",
      "form": "aff",
      "grammar_tags": [
        "DERIVATIVES-TERMINOLOGY",
        "RISK-LANGUAGE",
        "QUANTITATIVE-TERMS",
        "HEDGING-CONCEPTS"
      ]
    },
    {
      "id": "Lv6-D4-S23-017",
      "kr": "옵션 거래가 실행되었습니다. (완성 2)",
      "en": "Options trading has been executed. (completion variant 2)",
      "form": "aff",
      "grammar_tags": [
        "DERIVATIVES-TERMINOLOGY",
        "RISK-LANGUAGE",
        "QUANTITATIVE-TERMS",
        "HEDGING-CONCEPTS"
      ]
    },
    {
      "id": "Lv6-D4-S23-018",
      "kr": "옵션 거래가 실행되었습니다. (완성 3)",
      "en": "Options trading has been executed. (completion variant 3)",
      "form": "aff",
      "grammar_tags": [
        "DERIVATIVES-TERMINOLOGY",
        "RISK-LANGUAGE",
        "QUANTITATIVE-TERMS",
        "HEDGING-CONCEPTS"
      ]
    },
    {
      "id": "Lv6-D4-S23-019",
      "kr": "옵션 거래가 실행되었습니다. (완성 4)",
      "en": "Options trading has been executed. (completion variant 4)",
      "form": "aff",
      "grammar_tags": [
        "DERIVATIVES-TERMINOLOGY",
        "RISK-LANGUAGE",
        "QUANTITATIVE-TERMS",
        "HEDGING-CONCEPTS"
      ]
    },
    {
      "id": "Lv6-D4-S23-020",
      "kr": "옵션 거래가 실행되었습니다. (완성 5)",
      "en": "Options trading has been executed. (completion variant 5)",
      "form": "aff",
      "grammar_tags": [
        "DERIVATIVES-TERMINOLOGY",
        "RISK-LANGUAGE",
        "QUANTITATIVE-TERMS",
        "HEDGING-CONCEPTS"
      ]
    },
    {
      "id": "Lv6-D4-S23-021",
      "kr": "선물 계약을 통해 위험을 관리합니다. (완성 1)",
      "en": "We manage risk through futures contracts. (completion variant 1)",
      "form": "aff",
      "grammar_tags": [
        "DERIVATIVES-TERMINOLOGY",
        "RISK-LANGUAGE",
        "QUANTITATIVE-TERMS",
        "HEDGING-CONCEPTS"
      ]
    },
    {
      "id": "Lv6-D4-S23-022",
      "kr": "선물 계약을 통해 위험을 관리합니다. (완성 2)",
      "en": "We manage risk through futures contracts. (completion variant 2)",
      "form": "aff",
      "grammar_tags": [
        "DERIVATIVES-TERMINOLOGY",
        "RISK-LANGUAGE",
        "QUANTITATIVE-TERMS",
        "HEDGING-CONCEPTS"
      ]
    },
    {
      "id": "Lv6-D4-S23-023",
      "kr": "선물 계약을 통해 위험을 관리합니다. (완성 3)",
      "en": "We manage risk through futures contracts. (completion variant 3)",
      "form": "aff",
      "grammar_tags": [
        "DERIVATIVES-TERMINOLOGY",
        "RISK-LANGUAGE",
        "QUANTITATIVE-TERMS",
        "HEDGING-CONCEPTS"
      ]
    },
    {
      "id": "Lv6-D4-S23-024",
      "kr": "선물 계약을 통해 위험을 관리합니다. (완성 4)",
      "en": "We manage risk through futures contracts. (completion variant 4)",
      "form": "aff",
      "grammar_tags": [
        "DERIVATIVES-TERMINOLOGY",
        "RISK-LANGUAGE",
        "QUANTITATIVE-TERMS",
        "HEDGING-CONCEPTS"
      ]
    },
    {
      "id": "Lv6-D4-S23-025",
      "kr": "선물 계약을 통해 위험을 관리합니다. (완성 5)",
      "en": "We manage risk through futures contracts. (completion variant 5)",
      "form": "aff",
      "grammar_tags": [
        "DERIVATIVES-TERMINOLOGY",
        "RISK-LANGUAGE",
        "QUANTITATIVE-TERMS",
        "HEDGING-CONCEPTS"
      ]
    },
    {
      "id": "Lv6-D4-S23-026",
      "kr": "변동성이 증가하고 있습니다. (완성 1)",
      "en": "Volatility is increasing. (completion variant 1)",
      "form": "aff",
      "grammar_tags": [
        "DERIVATIVES-TERMINOLOGY",
        "RISK-LANGUAGE",
        "QUANTITATIVE-TERMS",
        "HEDGING-CONCEPTS"
      ]
    },
    {
      "id": "Lv6-D4-S23-027",
      "kr": "변동성이 증가하고 있습니다. (완성 2)",
      "en": "Volatility is increasing. (completion variant 2)",
      "form": "aff",
      "grammar_tags": [
        "DERIVATIVES-TERMINOLOGY",
        "RISK-LANGUAGE",
        "QUANTITATIVE-TERMS",
        "HEDGING-CONCEPTS"
      ]
    },
    {
      "id": "Lv6-D4-S23-028",
      "kr": "변동성이 증가하고 있습니다. (완성 3)",
      "en": "Volatility is increasing. (completion variant 3)",
      "form": "aff",
      "grammar_tags": [
        "DERIVATIVES-TERMINOLOGY",
        "RISK-LANGUAGE",
        "QUANTITATIVE-TERMS",
        "HEDGING-CONCEPTS"
      ]
    },
    {
      "id": "Lv6-D4-S23-029",
      "kr": "변동성이 증가하고 있습니다. (완성 4)",
      "en": "Volatility is increasing. (completion variant 4)",
      "form": "aff",
      "grammar_tags": [
        "DERIVATIVES-TERMINOLOGY",
        "RISK-LANGUAGE",
        "QUANTITATIVE-TERMS",
        "HEDGING-CONCEPTS"
      ]
    },
    {
      "id": "Lv6-D4-S23-030",
      "kr": "변동성이 증가하고 있습니다. (완성 5)",
      "en": "Volatility is increasing. (completion variant 5)",
      "form": "aff",
      "grammar_tags": [
        "DERIVATIVES-TERMINOLOGY",
        "RISK-LANGUAGE",
        "QUANTITATIVE-TERMS",
        "HEDGING-CONCEPTS"
      ]
    },
    {
      "id": "Lv6-D4-S23-031",
      "kr": "위험가치가 계산되었습니다. (완성 1)",
      "en": "Value-at-risk has been calculated. (completion variant 1)",
      "form": "neg",
      "grammar_tags": [
        "DERIVATIVES-TERMINOLOGY",
        "RISK-LANGUAGE",
        "QUANTITATIVE-TERMS",
        "HEDGING-CONCEPTS"
      ]
    },
    {
      "id": "Lv6-D4-S23-032",
      "kr": "위험가치가 계산되었습니다. (완성 2)",
      "en": "Value-at-risk has been calculated. (completion variant 2)",
      "form": "neg",
      "grammar_tags": [
        "DERIVATIVES-TERMINOLOGY",
        "RISK-LANGUAGE",
        "QUANTITATIVE-TERMS",
        "HEDGING-CONCEPTS"
      ]
    },
    {
      "id": "Lv6-D4-S23-033",
      "kr": "위험가치가 계산되었습니다. (완성 3)",
      "en": "Value-at-risk has been calculated. (completion variant 3)",
      "form": "neg",
      "grammar_tags": [
        "DERIVATIVES-TERMINOLOGY",
        "RISK-LANGUAGE",
        "QUANTITATIVE-TERMS",
        "HEDGING-CONCEPTS"
      ]
    },
    {
      "id": "Lv6-D4-S23-034",
      "kr": "위험가치가 계산되었습니다. (완성 4)",
      "en": "Value-at-risk has been calculated. (completion variant 4)",
      "form": "neg",
      "grammar_tags": [
        "DERIVATIVES-TERMINOLOGY",
        "RISK-LANGUAGE",
        "QUANTITATIVE-TERMS",
        "HEDGING-CONCEPTS"
      ]
    },
    {
      "id": "Lv6-D4-S23-035",
      "kr": "위험가치가 계산되었습니다. (완성 5)",
      "en": "Value-at-risk has been calculated. (completion variant 5)",
      "form": "neg",
      "grammar_tags": [
        "DERIVATIVES-TERMINOLOGY",
        "RISK-LANGUAGE",
        "QUANTITATIVE-TERMS",
        "HEDGING-CONCEPTS"
      ]
    },
    {
      "id": "Lv6-D4-S23-036",
      "kr": "스트레스 테스트를 실시했습니다. (완성 1)",
      "en": "We conducted stress testing. (completion variant 1)",
      "form": "neg",
      "grammar_tags": [
        "DERIVATIVES-TERMINOLOGY",
        "RISK-LANGUAGE",
        "QUANTITATIVE-TERMS",
        "HEDGING-CONCEPTS"
      ]
    },
    {
      "id": "Lv6-D4-S23-037",
      "kr": "스트레스 테스트를 실시했습니다. (완성 2)",
      "en": "We conducted stress testing. (completion variant 2)",
      "form": "neg",
      "grammar_tags": [
        "DERIVATIVES-TERMINOLOGY",
        "RISK-LANGUAGE",
        "QUANTITATIVE-TERMS",
        "HEDGING-CONCEPTS"
      ]
    },
    {
      "id": "Lv6-D4-S23-038",
      "kr": "스트레스 테스트를 실시했습니다. (완성 3)",
      "en": "We conducted stress testing. (completion variant 3)",
      "form": "neg",
      "grammar_tags": [
        "DERIVATIVES-TERMINOLOGY",
        "RISK-LANGUAGE",
        "QUANTITATIVE-TERMS",
        "HEDGING-CONCEPTS"
      ]
    },
    {
      "id": "Lv6-D4-S23-039",
      "kr": "스트레스 테스트를 실시했습니다. (완성 4)",
      "en": "We conducted stress testing. (completion variant 4)",
      "form": "neg",
      "grammar_tags": [
        "DERIVATIVES-TERMINOLOGY",
        "RISK-LANGUAGE",
        "QUANTITATIVE-TERMS",
        "HEDGING-CONCEPTS"
      ]
    },
    {
      "id": "Lv6-D4-S23-040",
      "kr": "스트레스 테스트를 실시했습니다. (완성 5)",
      "en": "We conducted stress testing. (completion variant 5)",
      "form": "neg",
      "grammar_tags": [
        "DERIVATIVES-TERMINOLOGY",
        "RISK-LANGUAGE",
        "QUANTITATIVE-TERMS",
        "HEDGING-CONCEPTS"
      ]
    },
    {
      "id": "Lv6-D4-S23-041",
      "kr": "거래상대방 위험이 평가되었습니다. (완성 1)",
      "en": "Counterparty risk has been assessed. (completion variant 1)",
      "form": "wh_q",
      "grammar_tags": [
        "DERIVATIVES-TERMINOLOGY",
        "RISK-LANGUAGE",
        "QUANTITATIVE-TERMS",
        "HEDGING-CONCEPTS"
      ]
    },
    {
      "id": "Lv6-D4-S23-042",
      "kr": "거래상대방 위험이 평가되었습니다. (완성 2)",
      "en": "Counterparty risk has been assessed. (completion variant 2)",
      "form": "wh_q",
      "grammar_tags": [
        "DERIVATIVES-TERMINOLOGY",
        "RISK-LANGUAGE",
        "QUANTITATIVE-TERMS",
        "HEDGING-CONCEPTS"
      ]
    },
    {
      "id": "Lv6-D4-S23-043",
      "kr": "거래상대방 위험이 평가되었습니다. (완성 3)",
      "en": "Counterparty risk has been assessed. (completion variant 3)",
      "form": "wh_q",
      "grammar_tags": [
        "DERIVATIVES-TERMINOLOGY",
        "RISK-LANGUAGE",
        "QUANTITATIVE-TERMS",
        "HEDGING-CONCEPTS"
      ]
    },
    {
      "id": "Lv6-D4-S23-044",
      "kr": "거래상대방 위험이 평가되었습니다. (완성 4)",
      "en": "Counterparty risk has been assessed. (completion variant 4)",
      "form": "wh_q",
      "grammar_tags": [
        "DERIVATIVES-TERMINOLOGY",
        "RISK-LANGUAGE",
        "QUANTITATIVE-TERMS",
        "HEDGING-CONCEPTS"
      ]
    },
    {
      "id": "Lv6-D4-S23-045",
      "kr": "거래상대방 위험이 평가되었습니다. (완성 5)",
      "en": "Counterparty risk has been assessed. (completion variant 5)",
      "form": "wh_q",
      "grammar_tags": [
        "DERIVATIVES-TERMINOLOGY",
        "RISK-LANGUAGE",
        "QUANTITATIVE-TERMS",
        "HEDGING-CONCEPTS"
      ]
    },
    {
      "id": "Lv6-D4-S23-046",
      "kr": "담보가 제공되었습니다. (완성 1)",
      "en": "Collateral has been provided. (completion variant 1)",
      "form": "wh_q",
      "grammar_tags": [
        "DERIVATIVES-TERMINOLOGY",
        "RISK-LANGUAGE",
        "QUANTITATIVE-TERMS",
        "HEDGING-CONCEPTS"
      ]
    },
    {
      "id": "Lv6-D4-S23-047",
      "kr": "담보가 제공되었습니다. (완성 2)",
      "en": "Collateral has been provided. (completion variant 2)",
      "form": "wh_q",
      "grammar_tags": [
        "DERIVATIVES-TERMINOLOGY",
        "RISK-LANGUAGE",
        "QUANTITATIVE-TERMS",
        "HEDGING-CONCEPTS"
      ]
    },
    {
      "id": "Lv6-D4-S23-048",
      "kr": "담보가 제공되었습니다. (완성 3)",
      "en": "Collateral has been provided. (completion variant 3)",
      "form": "wh_q",
      "grammar_tags": [
        "DERIVATIVES-TERMINOLOGY",
        "RISK-LANGUAGE",
        "QUANTITATIVE-TERMS",
        "HEDGING-CONCEPTS"
      ]
    },
    {
      "id": "Lv6-D4-S23-049",
      "kr": "담보가 제공되었습니다. (완성 4)",
      "en": "Collateral has been provided. (completion variant 4)",
      "form": "wh_q",
      "grammar_tags": [
        "DERIVATIVES-TERMINOLOGY",
        "RISK-LANGUAGE",
        "QUANTITATIVE-TERMS",
        "HEDGING-CONCEPTS"
      ]
    },
    {
      "id": "Lv6-D4-S23-050",
      "kr": "담보가 제공되었습니다. (완성 5)",
      "en": "Collateral has been provided. (completion variant 5)",
      "form": "wh_q",
      "grammar_tags": [
        "DERIVATIVES-TERMINOLOGY",
        "RISK-LANGUAGE",
        "QUANTITATIVE-TERMS",
        "HEDGING-CONCEPTS"
      ]
    }
  ],
  "forms_distribution": {
    "aff": 30,
    "neg": 10,
    "wh_q": 10
  },
  "grammar_meta": [
    "DERIVATIVES-TERMINOLOGY",
    "RISK-LANGUAGE",
    "QUANTITATIVE-TERMS",
    "HEDGING-CONCEPTS"
  ],
  "status": "generated",
  "batch": "L6_Professional_Batch2"
}