{
  "stage_id": "Lv8-C5-S29",
  "title": "Stage Lv8-C5-S29",
  "description": "Level 8 grammar practice focusing on stage-specific patterns and expressions.",
  "grammar_pattern": "Basic sentence patterns",
  "examples": [
    "Furthermore, the data suggests a clear trend toward improvement.",
    "Nevertheless, we must remain cautious about potential risks."
  ],
  "learning_points": "Level 8 target grammar and expressions with practical usage examples",
  "phase": 1,
  "stage_number": 29,
  "count": 8,
  "sentences": [
    {
      "id": "Lv8-C5-S29-001",
      "kr": "게다가 데이터는 개선 방향으로의 명확한 추세를 시사합니다.",
      "en": "Furthermore, the data suggests a clear trend toward improvement.",
      "form": "aff"
    },
    {
      "id": "Lv8-C5-S29-002",
      "kr": "그럼에도 불구하고 잠재적 위험에 대해서는 신중을 기해야 합니다.",
      "en": "Nevertheless, we must remain cautious about potential risks.",
      "form": "aff"
    },
    {
      "id": "Lv8-C5-S29-003",
      "kr": "그 결과 팀은 새로운 절차를 성공적으로 구현했습니다.",
      "en": "Subsequently, the team implemented the new procedures successfully.",
      "form": "aff"
    },
    {
      "id": "Lv8-C5-S29-004",
      "kr": "더욱이 이 접근법은 비용 효율적이기도 합니다.",
      "en": "Moreover, this approach is also cost-effective.",
      "form": "aff"
    },
    {
      "id": "Lv8-C5-S29-005",
      "kr": "그러나 여전히 해결해야 할 문제들이 있습니다.",
      "en": "Nonetheless, there are still issues that need to be addressed.",
      "form": "aff"
    },
    {
      "id": "Lv8-C5-S29-006",
      "kr": "따라서 우리는 전략을 재평가해야 합니다.",
      "en": "Consequently, we need to reassess our strategy.",
      "form": "aff"
    },
    {
      "id": "Lv8-C5-S29-007",
      "kr": "마찬가지로 다른 부서에서도 비슷한 결과를 얻었습니다.",
      "en": "Likewise, other departments achieved similar results.",
      "form": "aff"
    },
    {
      "id": "Lv8-C5-S29-008",
      "kr": "결국 모든 노력이 성공으로 이어졌습니다.",
      "en": "Ultimately, all efforts led to success.",
      "form": "aff"
    }
  ],
  "forms_distribution": {
    "aff": 8,
    "neg": 0,
    "wh_q": 0,
    "unknown": 0
  },
  "status": "incomplete",
  "batch": "L8_Reorganization_Batch",
  "metadata": {
    "reorganized_at": "2025-08-28T11:08:55.565Z",
    "reorganization_version": "2.2.0",
    "source_files": [
      "web_app\\public\\patterns\\banks\\level_8\\Lv8-C5-S29_bank.json"
    ]
  }
}