{
  "stage_id": "Lv8-C1-S02",
  "title": "Stage Lv8-C1-S02",
  "description": "Level 8 grammar practice focusing on stage-specific patterns and expressions.",
  "grammar_pattern": "Basic sentence patterns",
  "examples": [
    "So determined was she that nothing could stop her.",
    "Such was the impact that everyone remembered it."
  ],
  "learning_points": "Level 8 target grammar and expressions with practical usage examples",
  "phase": 1,
  "stage_number": 2,
  "count": 8,
  "sentences": [
    {
      "id": "Lv8-C1-S02-001",
      "kr": "그녀가 너무나 결심이 굳어서 아무것도 그녀를 막을 수 없었습니다.",
      "en": "So determined was she that nothing could stop her.",
      "form": "aff"
    },
    {
      "id": "Lv8-C1-S02-002",
      "kr": "그 충격이 워낙 컸던지라 모든 사람이 기억하고 있습니다.",
      "en": "Such was the impact that everyone remembered it.",
      "form": "aff"
    },
    {
      "id": "Lv8-C1-S02-003",
      "kr": "우리가 도착하자마자 회의가 시작되었습니다.",
      "en": "Barely had we arrived when the meeting started.",
      "form": "aff"
    },
    {
      "id": "Lv8-C1-S02-004",
      "kr": "그 소식이 너무나 놀라워서 말문이 막혔습니다.",
      "en": "So surprising was the news that we were speechless.",
      "form": "aff"
    },
    {
      "id": "Lv8-C1-S02-005",
      "kr": "그의 재능이 워낙 뛰어나서 모든 사람이 감탄했습니다.",
      "en": "Such was his talent that everyone admired him.",
      "form": "aff"
    },
    {
      "id": "Lv8-C1-S02-006",
      "kr": "간신히 문제를 해결했더니 새로운 도전이 기다리고 있었습니다.",
      "en": "Hardly had we solved the problem when a new challenge awaited.",
      "form": "aff"
    },
    {
      "id": "Lv8-C1-S02-007",
      "kr": "그 상황이 너무나 복잡해서 아무도 이해할 수 없었습니다.",
      "en": "So complex was the situation that nobody could understand it.",
      "form": "aff"
    },
    {
      "id": "Lv8-C1-S02-008",
      "kr": "그의 헌신이 워낙 깊어서 모든 사람이 존경했습니다.",
      "en": "Such was his dedication that everyone respected him.",
      "form": "aff"
    }
  ],
  "forms_distribution": {
    "aff": 8,
    "neg": 0,
    "wh_q": 0,
    "unknown": 0
  },
  "status": "incomplete",
  "batch": "L8_Reorganization_Batch",
  "metadata": {
    "reorganized_at": "2025-08-28T11:08:55.540Z",
    "reorganization_version": "2.2.0",
    "source_files": [
      "web_app\\public\\patterns\\banks\\level_8\\Lv8-C1-S02_bank.json"
    ]
  }
}