{
  "stage_id": "Lv8-C6-S40",
  "title": "Stage Lv8-C6-S40",
  "description": "Level 8 grammar practice focusing on stage-specific patterns and expressions.",
  "grammar_pattern": "Basic sentence patterns",
  "examples": [
    "This phenomenon can be attributed to several underlying factors.",
    "The data demonstrates a significant correlation between these variables."
  ],
  "learning_points": "Level 8 target grammar and expressions with practical usage examples",
  "phase": 1,
  "stage_number": 40,
  "count": 8,
  "sentences": [
    {
      "id": "Lv8-C6-S40-001",
      "kr": "이 현상은 여러 근본적인 요인들에 기인한다고 볼 수 있습니다.",
      "en": "This phenomenon can be attributed to several underlying factors.",
      "form": "aff"
    },
    {
      "id": "Lv8-C6-S40-002",
      "kr": "데이터는 이들 변수 간의 유의미한 상관관계를 보여줍니다.",
      "en": "The data demonstrates a significant correlation between these variables.",
      "form": "aff"
    },
    {
      "id": "Lv8-C6-S40-003",
      "kr": "이 문제를 최대한 신중하게 검토하는 것이 필수적입니다.",
      "en": "It is imperative that we examine this matter with utmost care.",
      "form": "aff"
    },
    {
      "id": "Lv8-C6-S40-004",
      "kr": "연구 결과는 이론적 가설을 강력하게 뒷받침합니다.",
      "en": "The research findings provide substantial support for the theoretical hypothesis.",
      "form": "aff"
    },
    {
      "id": "Lv8-C6-S40-005",
      "kr": "이 접근법의 효과는 다양한 실증적 증거에 의해 입증되었습니다.",
      "en": "The efficacy of this approach has been validated through various empirical evidence.",
      "form": "aff"
    },
    {
      "id": "Lv8-C6-S40-006",
      "kr": "현재의 분석은 기존 연구와 일치하는 결과를 나타냅니다.",
      "en": "The current analysis yields results consistent with previous studies.",
      "form": "aff"
    },
    {
      "id": "Lv8-C6-S40-007",
      "kr": "이 방법론은 연구의 타당성과 신뢰성을 보장합니다.",
      "en": "This methodology ensures the validity and reliability of the research.",
      "form": "aff"
    },
    {
      "id": "Lv8-C6-S40-008",
      "kr": "결론적으로, 제시된 증거는 가설을 명확히 뒷받침합니다.",
      "en": "In conclusion, the presented evidence unequivocally supports the hypothesis.",
      "form": "aff"
    }
  ],
  "forms_distribution": {
    "aff": 8,
    "neg": 0,
    "wh_q": 0,
    "unknown": 0
  },
  "status": "incomplete",
  "batch": "L8_Reorganization_Batch",
  "metadata": {
    "reorganized_at": "2025-08-28T11:08:55.576Z",
    "reorganization_version": "2.2.0",
    "source_files": [
      "web_app\\public\\patterns\\banks\\level_8\\Lv8-C6-S40_bank.json"
    ]
  }
}